similarity_index_of_label_graph_package/__init__.py
similarity_index_of_label_graph_package/similarity_index_of_label_graph_module.py
similarity_index_of_label_graph-2.0.1.dist-info/LICENSE
similarity_index_of_label_graph-2.0.1.dist-info/METADATA
similarity_index_of_label_graph-2.0.1.dist-info/WHEEL
similarity_index_of_label_graph-2.0.1.dist-info/top_level.txt
similarity_index_of_label_graph-2.0.1.dist-info/RECORD
