Metadata-Version: 2.1
Name: similarity-index-of-label-graph
Version: 2.0.1
Summary: calculate the similarity index of the label graph pairs package in python.
Home-page: https://github.com/fsssosei/similarity_index_of_label_graph
Author: sosei
Author-email: fss.sosei@gmail.com
License: GNU Affero General Public License v3
Keywords: Graph,Similarity,Embedding,Measure
Platform: UNKNOWN
Classifier: Development Status :: 5 - Production/Stable
Classifier: License :: OSI Approved :: GNU Affero General Public License v3
Classifier: Programming Language :: Python :: 3.7
Requires-Python: >=3.7
Requires-Dist: networkx (>=2.4)
Requires-Dist: numpy (>=1.18.2)
Requires-Dist: scipy (>=1.4.1)
